koda_validate/__init__.py
koda_validate/_generics.py
koda_validate/_internal.py
koda_validate/base.py
koda_validate/boolean.py
koda_validate/bytes.py
koda_validate/coerce.py
koda_validate/dataclasses.py
koda_validate/decimal.py
koda_validate/dictionary.py
koda_validate/errors.py
koda_validate/float.py
koda_validate/generic.py
koda_validate/integer.py
koda_validate/is_type.py
koda_validate/list.py
koda_validate/maybe.py
koda_validate/namedtuple.py
koda_validate/none.py
koda_validate/py.typed
koda_validate/serialization/__init__.py
koda_validate/serialization/base.py
koda_validate/serialization/errors.py
koda_validate/serialization/json_schema.py
koda_validate/set.py
koda_validate/signature.py
koda_validate/string.py
koda_validate/time.py
koda_validate/tuple.py
koda_validate/typeddict.py
koda_validate/typehints.py
koda_validate/union.py
koda_validate/uuid.py
koda_validate/valid.py
koda_validate-5.1.0.dist-info/LICENSE
koda_validate-5.1.0.dist-info/METADATA
koda_validate-5.1.0.dist-info/WHEEL
koda_validate-5.1.0.dist-info/RECORD
