Metadata-Version: 2.3
Name: koda-validate
Version: 5.1.0
Summary: Typesafe, composable validation
License: MIT
Keywords: validation,type hints,asyncio,serialization,typesafe,validate,validators,predicate,processor
Author: Keith Philpott
Requires-Python: >=3.9,<4.0
Classifier: Development Status :: 5 - Production/Stable
Classifier: Environment :: MacOS X
Classifier: Environment :: Web Environment
Classifier: Intended Audience :: Developers
Classifier: License :: OSI Approved :: MIT License
Classifier: Operating System :: MacOS
Classifier: Operating System :: Microsoft :: Windows
Classifier: Operating System :: POSIX :: Linux
Classifier: Operating System :: Unix
Classifier: Programming Language :: Python :: 3
Classifier: Programming Language :: Python :: 3.9
Classifier: Programming Language :: Python :: 3.10
Classifier: Programming Language :: Python :: 3.11
Classifier: Programming Language :: Python :: 3.12
Classifier: Programming Language :: Python :: 3.13
Classifier: Topic :: Software Development :: Libraries :: Python Modules
Classifier: Topic :: Utilities
Classifier: Typing :: Typed
Requires-Dist: koda (==1.4.0)
Project-URL: Documentation, https://koda-validate.readthedocs.io/en/stable/
Project-URL: Homepage, https://github.com/keithasaurus/koda-validate
